kdens/__init__.py
kdens/kdens.py
kdens/version.py
kdeepensemble-0.3.2.dist-info/LICENSE
kdeepensemble-0.3.2.dist-info/METADATA
kdeepensemble-0.3.2.dist-info/WHEEL
kdeepensemble-0.3.2.dist-info/top_level.txt
kdeepensemble-0.3.2.dist-info/RECORD
