Metadata-Version: 2.1
Name: kdeepensemble
Version: 0.3.2
Summary: Deep ensembles for Keras
Home-page: https://ur-whitelab.github.io/exmol/
Author: Andrew White
Author-email: andrew.white@rochester.edu
License: MIT
Classifier: Programming Language :: Python :: 3
Classifier: License :: OSI Approved :: MIT License
Classifier: Operating System :: OS Independent
Classifier: Topic :: Scientific/Engineering :: Artificial Intelligence
License-File: LICENSE
Requires-Dist: numpy
Requires-Dist: tensorflow
